README.md
setup.cfg
setup.py
tele_bot_push.egg-info/PKG-INFO
tele_bot_push.egg-info/SOURCES.txt
tele_bot_push.egg-info/dependency_links.txt
tele_bot_push.egg-info/requires.txt
tele_bot_push.egg-info/top_level.txt
telegram_bot_push/__init__.py
telegram_bot_push/bot.py
telegram_bot_push/bot_push.py
telegram_bot_push/small_functions.py