Metadata-Version: 2.1
Name: tele-bot-push
Version: 0.0.2.1
Summary: Telegram机器人发送消息
Home-page: https://github.com/BuGTEa/Telegram-Bot-push
Author: BuGTEa
Author-email: noreply@sir7878.com
License: UNKNOWN
Platform: UNKNOWN
